gridgs/sdk/api/__init__.py
gridgs/sdk/api/base_client.py
gridgs/sdk/api/client.py
gridgs/sdk/api/frame_client.py
gridgs/sdk/api/params.py
gridgs/sdk/api/satellite_client.py
gridgs/sdk/api/session_client.py
gridgs/sdk/auth/__init__.py
gridgs/sdk/auth/client.py
gridgs/sdk/entity/__init__.py
gridgs/sdk/entity/company.py
gridgs/sdk/entity/frame.py
gridgs/sdk/entity/ground_station.py
gridgs/sdk/entity/horizontal_coords.py
gridgs/sdk/entity/satellite.py
gridgs/sdk/entity/session.py
gridgs/sdk/entity/session_event.py
gridgs/sdk/entity/tle.py
gridgs/sdk/entity/token.py
gridgs/sdk/event/__init__.py
gridgs/sdk/event/subscriber.py
gridgs/sdk/logger_fields/__init__.py
gridgs/sdk/logger_fields/log_fields.py
gridgs/sdk/mqtt/__init__.py
gridgs/sdk/mqtt/client.py
gridgs/sdk/mqtt/interface.py
gridgs/sdk/mqtt/exceptions/__init__.py
gridgs/sdk/mqtt/exceptions/exceptions.py
gridgs/sdk/ssl/__init__.py
gridgs/sdk/ssl/settings.py
gridgs_sdk-1.0.25.dist-info/licenses/LICENSE.txt
gridgs_sdk-1.0.25.dist-info/METADATA
gridgs_sdk-1.0.25.dist-info/WHEEL
gridgs_sdk-1.0.25.dist-info/top_level.txt
gridgs_sdk-1.0.25.dist-info/RECORD
