Metadata-Version: 2.4
Name: gridgs-sdk
Version: 1.0.25
Summary: Python SDK to simplify integration with GRID services
Author-email: 5OKB <dev@5okb.com>
Project-URL: Homepage, https://github.com/5OKB/grid-python-sdk
Project-URL: Bug Tracker, https://github.com/5OKB/grid-python-sdk/issues
Classifier: Programming Language :: Python :: 3
Classifier: License :: OSI Approved :: MIT License
Classifier: Operating System :: OS Independent
Requires-Python: >=3.7
License-File: LICENSE.txt
Requires-Dist: paho-mqtt==2.1.*
Requires-Dist: python-keycloak==4.*
Dynamic: license-file
